travisci/Preferences.py
travisci/SemanticVersion.py
travisci/Singleton.py
travisci/TravisCli.py
travisci/__init__.py
travisci/exceptions/PreferencesLocationNotSet.py
travisci/exceptions/UnsupportedOperation.py
travisci/exceptions/__init__.py
travisci/resources/__init__.py
travisci/resources/loggingConfiguration.json
traviscli-0.3.2.dist-info/LICENSE
traviscli-0.3.2.dist-info/METADATA
traviscli-0.3.2.dist-info/WHEEL
traviscli-0.3.2.dist-info/entry_points.txt
traviscli-0.3.2.dist-info/top_level.txt
traviscli-0.3.2.dist-info/RECORD
