Metadata-Version: 2.1
Name: traviscli
Version: 0.3.2
Summary: A build help tool
Home-page: https://github.com/hasii2011/travisci-cli
Author-email: Humberto.A.Sanchez.II@gmail.com
License-File: LICENSE
Requires-Dist: click
Requires-Dist: PyTravisCI
